Workbook

Sheet Banque_CR
A1: ID | B1: Examen | C1: N° thématique | D1: ID_Thématique | E1: ID_Chapitre | F1: Question | G1: Réponse A | H1: Réponse B | I1: Réponse C | J1: Réponse D | K1: Bonne réponse | L1: Explication pédagogique | M1: Astuce mémoire | N1: Difficulté | O1: Compétence | P1: Mots-clés | Q1: Ressources à revoir | R1: Diagnostic | S1: Révision | T1: Examen blanc | U1: Statut | V1: Fichier source | W1: Origine des distracteurs
A2: CR-T1-001 | B2: CR | C2: 1 | D2: Principes et valeurs de la République | E2: Chapitre 6 — Contrat d’engagement et citoyenneté | F2: Parmi les propositions suivantes, laquelle constitue une participation citoyenne ? | G2: Obtenir une carte d'identité française. | H2: S'inscrire à la Sécurité sociale. | I2: Voter aux élections. | J2: Travailler dans une entreprise. | K2: C | L2: La participation citoyenne consiste à prendre part à la vie démocratique du pays. Le vote est l'une des principales formes de participation citoyenne. | M2: Retenez le mot-clé : Citoyenneté = droit de voter aux élections | N2: 🟢 Facile | O2: Connaître les formes de participation à la vie démocratique. | P2: Citoyenneté; Vote; Élections | Q2: 📚 Thématique 1 – Principes et valeurs de la République 📖 Glossaire - Citoyenneté - Vote | R2: Oui | S2: Oui | T2: Oui | U2: À vérifier | V2: QUESTIONS_THEMATIQUE_1(1).md | W2: QCM source
A3: CR-T1-002 | B3: CR | C3: 1 | D3: Principes et valeurs de la République | E3: CH01_Principes et valeurs | F3: Que garantit la liberté d'expression ? | G3: Le droit d'insulter les autres. | H3: Le droit de diffamer. | I3: Le droit d'exprimer librement ses opinions dans le respect de la loi. | J3: Le droit d'inciter à la haine. | K3: C | L3: La liberté d'expression est une liberté fondamentale. Elle permet à chacun d'exprimer ses idées, tout en respectant les lois et les autres personnes. | M3: Retenez le mot-clé : Liberté d'expression = exprimer ses opinions | N3: 🟢 Facile | O3: Comprendre les libertés fondamentales. | P3: Liberté d'expression; Opinion; Libertés | Q3: 📚 Thématique 1 – Libertés fondamentales 📖 Glossaire - Liberté d'expression | R3: Oui | S3: Oui | T3: Oui | U3: À vérifier | V3: QUESTIONS_THEMATIQUE_1(1).md | W3: Réponses à ne pas accepter + banque thématique
A4: CR-T1-003 | B4: CR | C4: 1 | D4: Principes et valeurs de la République | F4: À quoi sert un titre de séjour ? | G4: À obtenir automatiquement la nationalité française. | H4: À voter aux élections. | I4: À remplacer une carte d'identité. | J4: À autoriser un étranger à séjourner légalement en France. | K4: D | L4: Le titre de séjour est un document officiel qui autorise une personne étrangère à résider en France pendant une durée déterminée ou permanente, selon sa situation. | M4: Retenez le mot-clé : Titre de séjour = document pour habiter en France | N4: 🟡 Intermédiaire | O4: Connaître les principaux documents administratifs liés au séjour. | P4: Titre de séjour; Séjour; France | Q4: 📚 Thématique 1 – Vie administrative 📖 Glossaire - Titre de séjour | R4: Oui | S4: Oui | T4: Oui | U4: À vérifier | V4: QUESTIONS_THEMATIQUE_1(1).md | W4: Réponses à ne pas accepter + banque thématique
A5: CR-T1-004 | B5: CR | C5: 1 | D5: Principes et valeurs de la République | E5: Chapitre 1 — Principes et valeurs | F5: La liberté de circulation permet à toute personne de : | G5: S'installer sur n'importe quel terrain privé. | H5: Se déplacer librement sur le territoire national et à l'étranger. | I5: Conduire n'importe quel véhicule sans permis. | J5: Voyager librement sans papiers d'identité dans toute l'Europe. | K5: B | L5: La liberté de circulation permet à chacun de se déplacer librement, dans le respect des lois et des règles applicables. | M5: Retenez le mot-clé : Liberté de circulation = se déplacer | N5: 🟡 Intermédiaire | O5: Comprendre les libertés fondamentales. | P5: Liberté de circulation; Déplacement; France | Q5: 📚 Thématique 1 – Libertés fondamentales 📖 Glossaire - Liberté de circulation | R5: Oui | S5: Oui | T5: Oui | U5: À vérifier | V5: QUESTIONS_THEMATIQUE_1(1).md | W5: QCM source
A6: CR-T1-005 | B6: CR | C6: 1 | D6: Principes et valeurs de la République | E6: Chapitre 3 — Symboles de la République | F6: Sur quel site internet peut-on retrouver les symboles de la République française ? | G6: Sur le site de l'Élysée. | H6: Le site de la CAF. | I6: France Travail. | J6: Ameli. | K6: A | L6: Le site officiel de la Présidence de la République présente les symboles de la République française, notamment le drapeau, Marianne, la Marseillaise et la devise. | M6: Retenez : Site internet officiel montre les symboles | N6: 🟡 Intermédiaire | O6: Identifier les ressources officielles de la République française. | P6: Élysée; République; Symboles | Q6: 📚 Thématique 1 – Symboles de la République 📖 Glossaire - Symboles de la République | R6: Oui | S6: Oui | T6: Oui | U6: À vérifier | V6: QUESTIONS_THEMATIQUE_1(1).md | W6: Réponses à ne pas accepter + banque thématique
A7: CR-T1-006 | B7: CR | C7: 1 | D7: Principes et valeurs de la République | E7: Chapitre 3 — Symboles de la République | F7: Complétez ces paroles de la Marseillaise : « Aux armes [...] ! Formez vos bataillons. » | G7: Français. | H7: Soldats. | I7: Amis. | J7: Citoyens. | K7: D | L7: La Marseillaise est l'hymne national français. Chaque citoyen est invité à connaître ses paroles et leur signification. | M7: Retenez : Les citoyens = habitants de la France | N7: 🟡 Intermédiaire | O7: Connaître les symboles de la République. | P7: Marseillaise; Citoyens; Hymne national | Q7: 📚 Thématique 1 – Symboles de la République 📖 Glossaire - Marseillaise | R7: Oui | S7: Oui | T7: Oui | U7: À vérifier | V7: QUESTIONS_THEMATIQUE_1(1).md | W7: Réponses à ne pas accepter + banque thématique
A8: CR-T1-007 | B8: CR | C8: 1 | D8: Principes et valeurs de la République | E8: Chapitre 3 — Symboles de la République | F8: Complétez les paroles de la Marseillaise : « Allons enfants de la Patrie [...] » | G8: Le jour de gloire est arrivé. | H8: Le droit d'exprimer librement ses opinions dans le respect de la loi. | I8: À autoriser un étranger à séjourner légalement en France. | J8: Se déplacer librement sur le territoire national et à l'étranger. | K8: A | L8: Ces paroles ouvrent la Marseillaise, l'hymne national de la République française. | M8: Retenez : Gloire = grandeur | N8: 🟡 Intermédiaire | O8: Connaître les symboles de la République. | P8: Marseillaise; Hymne | Q8: 📚 Thématique 1 – Symboles de la République 📖 Glossaire - Marseillaise | R8: Oui | S8: Oui | T8: Oui | U8: À vérifier | V8: QUESTIONS_THEMATIQUE_1(1).md | W8: Banque thématique + génération éditoriale
A9: CR-T1-008 | B9: CR | C9: 1 | D9: Principes et valeurs de la République | E9: Chapitre 4 — Laïcité | F9: En application de la liberté individuelle, quelle proposition est correcte ? Une personne peut : | G9: Refuser de respecter les lois si elles sont contraires à ses principes. | H9: Imposer ses idées aux autres. | I9: Choisir ses propres règles. | J9: Choisir sa religion ou ne pas en avoir. | K9: D | L9: En France, chacun est libre de pratiquer une religion, d'en changer ou de ne pas avoir de religion. Cette liberté est protégée par la loi. | M9: Retenez : chacun peut choisir sa religion | N9: 🟡 Intermédiaire | O9: Comprendre les libertés individuelles. | P9: Religion; Liberté; Laïcité | Q9: 📚 Thématique 1 – Libertés fondamentales 📖 Glossaire - Liberté de conscience | R9: Oui | S9: Oui | T9: Oui | U9: À vérifier | V9: QUESTIONS_THEMATIQUE_1(1).md | W9: QCM source
A10: CR-T1-009 | B10: CR | C10: 1 | D10: Principes et valeurs de la République | E10: Chapitre 4 — Laïcité | F10: Concernant la pratique de la religion, quelle proposition est correcte ? | G10: Chacun est libre de pratiquer sa religion. | H10: Les signes religieux sont interdits dans la rue. | I10: La religion ne peut être pratiquée qu'à la maison. | J10: Les lieux de culte sont financés par tous les services publics. | K10: A | L10: La liberté religieuse est garantie en France. Chacun est libre de croire, de pratiquer sa religion ou de ne pas avoir de religion, dans le respect de la loi. | M10: Retenez : chacun peut choisir sa religion | N10: 🟡 Intermédiaire | O10: Comprendre la liberté religieuse. | P10: Religion; Liberté; Laïcité | Q10: 📚 Thématique 1 – Laïcité 📖 Glossaire - Liberté de religion | R10: Oui | S10: Oui | T10: Oui | U10: À vérifier | V10: QUESTIONS_THEMATIQUE_1(1).md | W10: QCM source
A11: CR-T1-010 | B11: CR | C11: 1 | D11: Principes et valeurs de la République | E11: Chapitre 1 — Principes et valeurs | F11: En tant que parent, peut-on refuser que son enfant participe aux cours de sport à l'école parce qu'ils sont mixtes ? | G11: Oui. | H11: Oui si les parents le souhaitent. | I11: Oui, dans tous les cas. | J11: Non. | K11: D | L11: Les cours de sport font partie des enseignements obligatoires. La mixité entre les filles et les garçons est un principe de l'école de la République. | M11: Retenez : Cours = obligatoire | N11: 🟡 Intermédiaire | O11: Connaître les principes de l'école de la République. | P11: École; Mixité; Sport; Égalité | Q11: 📚 Thématique 1 – École et République 📖 Glossaire - Mixité - École publique | R11: Oui | S11: Oui | T11: Oui | U11: À vérifier | V11: QUESTIONS_THEMATIQUE_1(1).md | W11: Réponses à ne pas accepter + banque thématique
A12: CR-T1-011 | B12: CR | C12: 1 | D12: Principes et valeurs de la République | E12: Chapitre 3 — Symboles de la République | F12: Quelle est la devise de la France ? | G12: Liberté, Justice, Egalité, | H12: Travail, Famille, Patrie. | I12: Liberté, Égalité, Fraternité. | J12: Égalité, Solidarité, Liberté, | K12: C | L12: La devise de la République française est « Liberté, Égalité, Fraternité ». Elle exprime les valeurs fondamentales de la République. | M12: Retenez : La devise = valeurs représentant la France | N12: 🟡 Intermédiaire | O12: Connaître les symboles de la République. | P12: Devise; République; Liberté; Égalité; Fraternité | Q12: 📚 Thématique 1 – Valeurs de la République 📖 Glossaire - Devise républicaine | R12: Oui | S12: Oui | T12: Oui | U12: À vérifier | V12: QUESTIONS_THEMATIQUE_1(1).md | W12: Réponses à ne pas accepter + banque thématique
A13: CR-T1-012 | B13: CR | C13: 1 | D13: Principes et valeurs de la République | E13: Chapitre 1 — Principes et valeurs | F13: La répudiation de sa femme est : | G13: Autorisée avec l'accord d'un juge. | H13: Interdite par la loi française. | I13: Légale si elle est prévue dans le contrat de mariage. | J13: Autorisée avec l'accord de la famille. | K13: B | L13: En France, les femmes et les hommes disposent des mêmes droits. La répudiation n'est pas reconnue par le droit français. | M13: Retenez le mot-clé : Égalité. | N13: 🟢 Facile | O13: Connaître le principe d'égalité entre les femmes et les hommes. | P13: Égalité; Mariage; Répudiation | Q13: 📚 Thématique 1 – Égalité 📖 Glossaire - Égalité femmes-hommes | R13: Oui | S13: Oui | T13: Oui | U13: À vérifier | V13: QUESTIONS_THEMATIQUE_1(1).md | W13: QCM source
A14: CR-T1-013 | B14: CR | C14: 1 | D14: Principes et valeurs de la République | E14: Chapitre 6 — Contrat d’engagement et citoyenneté | F14: Les impôts permettent de financer les dépenses publiques. Quelle proposition est correcte ? | G14: Les impôts servent uniquement à payer les élus. | H14: Les impôts sont facultatifs. | I14: Les impôts sont réservés aux entreprises. | J14: Les impôts financent les services publics et les équipements utiles à tous. | K14: D | L14: Les impôts servent à financer les écoles, les hôpitaux, les routes, la sécurité, la justice et de nombreux autres services publics. | M14: Retenez le mot-clé : Impôts. | N14: 🟡 Intermédiaire | O14: Comprendre le rôle des impôts. | P14: Impôts; Services publics; État | Q14: 📚 Thématique 1 – Citoyenneté 📖 Glossaire - Impôts | R14: Oui | S14: Oui | T14: Oui | U14: À vérifier | V14: QUESTIONS_THEMATIQUE_1(1).md | W14: QCM source
A15: CR-T1-014 | B15: CR | C15: 1 | D15: Principes et valeurs de la République | E15: Chapitre 3 — Symboles de la République | F15: Peut-on brûler publiquement un drapeau français ? | G15: Oui. | H15: Oui si c'est une manifestation. | I15: Non. | J15: Oui, dans tous les cas. | K15: C | L15: Le drapeau français est un symbole de la République. Les atteintes publiques à ce symbole sont encadrées et peuvent être sanctionnées par la loi. | M15: Retenez le mot-clé : Drapeau. | N15: 🟡 Intermédiaire | O15: Connaître les symboles de la République. | P15: Drapeau; République; Symbole | Q15: 📚 Thématique 1 – Symboles 📖 Glossaire - Drapeau français | R15: Oui | S15: Oui | T15: Oui | U15: À vérifier | V15: QUESTIONS_THEMATIQUE_1(1).md | W15: Réponses à ne pas accepter + banque thématique
A16: CR-T1-015 | B16: CR | C16: 1 | D16: Principes et valeurs de la République | E16: Chapitre 1 — Principes et valeurs | F16: Que fait l'État pour lutter contre les discriminations ? | G16: Il les autorise. | H16: Il ne fait rien. | I16: Il interdit les discriminations et les sanctionne par la loi. | J16: Cela dépend des situations. | K16: C | L16: La loi protège chaque personne contre les discriminations fondées notamment sur l'origine, le sexe, la religion, le handicap ou l'orientation sexuelle. | M16: Retenez le mot-clé : Discrimination. | N16: 🔴 Difficile | O16: Connaître le principe d'égalité et de non-discrimination. | P16: Discrimination; Égalité; Loi | Q16: 📚 Thématique 1 – Égalité 📖 Glossaire - Discrimination | R16: Oui | S16: Oui | T16: Oui | U16: À vérifier | V16: QUESTIONS_THEMATIQUE_1(1).md | W16: Réponses à ne pas accepter + banque thématique
... A149: CR-T4-021 | B149: CR | C149: 4 | D149: Histoire, géographie, patrimoine et culture | E149: Histoire de France | F149: Citez une mer ou un océan qui borde la France métropolitaine. | G149: La mer Méditerranée. | H149: L'océan indien. | I149: La mer Rouge. | J149: L'océan Pacifique. | K149: A | L149: La France métropolitaine est bordée par quatre espaces maritimes : la Manche, la mer du Nord, l'océan Atlantique et la mer Méditerranée. | M149: Retenez : 3 mers et 1 océan entourent la France - Mers : Méditerranée, Du Nord et la Manche - Océan : Atlantique | N149: 🔴 Difficile | O149: Connaître la géographie de la France. | P149: France; Mer; Océan; Littoral | Q149: 📚 Thématique 4 – Géographie 📖 Glossaire - Manche - Mer Méditerranée - Océan Atlantique | R149: Oui | S149: Oui | T149: Oui | U149: À vérifier | V149: QUESTIONS_THEMATIQUE_4.md | W149: Réponses à ne pas accepter + banque thématique
A150: CR-T4-022 | B150: CR | C150: 4 | D150: Histoire, géographie, patrimoine et culture | E150: Géographie de la France | F150: Quel pays a une frontière terrestre avec la France métropolitaine ? | G150: Royaume-Uni. | H150: Portugal. | I150: Autriche. | J150: Espagne. | K150: D | L150: La France métropolitaine partage une frontière terrestre avec huit pays. | N150: 🔴 Difficile | O150: Connaître les frontières de la France. | P150: Frontières; Pays voisins; France | Q150: 📚 Thématique 4 – Géographie 📖 Glossaire - Pays frontaliers | R150: Oui | S150: Oui | T150: Oui | U150: À vérifier | V150: QUESTIONS_THEMATIQUE_4.md | W150: Réponses à ne pas accepter + banque thématique
A151: CR-T4-023 | B151: CR | C151: 4 | D151: Histoire, géographie, patrimoine et culture | E151: Histoire de France | F151: Quelle ville française est un port maritime ? | G151: Clermont-Ferrand. | H151: Limoges. | I151: Marseille. | J151: Dijon. | K151: C | L151: Marseille est le plus grand port maritime français et l'un des plus importants ports de la mer Méditerranée. | M151: Retenez : Marseille = 1er port français | N151: 🟡 Intermédiaire | O151: Connaître la géographie économique de la France. | P151: Marseille; Port; Méditerranée | Q151: 📚 Thématique 4 – Géographie 📖 Glossaire - Port maritime | R151: Oui | S151: Oui | T151: Oui | U151: À vérifier | V151: QUESTIONS_THEMATIQUE_4.md | W151: QCM source
A152: CR-T4-024 | B152: CR | C152: 4 | D152: Histoire, géographie, patrimoine et culture | E152: Histoire de France | F152: Quelle mer se situe entre la France et l'Angleterre ? | G152: La mer du Nord. | H152: La mer Méditerranée. | I152: L'océan Atlantique. | J152: La Manche. | K152: D | L152: La Manche sépare la France de l'Angleterre. Elle est traversée notamment par le tunnel sous la Manche. | M152: Retenez le mot-clé : La Manche. | N152: 🟡 Intermédiaire | O152: Connaître la géographie de la France. | P152: Manche; Angleterre; France | Q152: 📚 Thématique 4 – Géographie 📖 Glossaire - Manche | R152: Oui | S152: Oui | T152: Oui | U152: À vérifier | V152: QUESTIONS_THEMATIQUE_4.md | W152: Réponses à ne pas accepter + banque thématique
A153: CR-T4-025 | B153: CR | C153: 4 | D153: Histoire, géographie, patrimoine et culture | E153: Géographie de la France | F153: Qu'est-ce que la France d'outre-mer ? | G153: Les pays voisins de la France. | H153: Les territoires français situés en dehors de l'Europe. | I153: Les anciennes colonies françaises. | J153: Les régions situées au nord de la France. | K153: B | L153: La France d'outre-mer regroupe les départements, régions, collectivités et territoires français situés en dehors de l'Europe, comme la Guadeloupe, La Réunion ou la Polynésie française. | M153: Retenez : La France d'outre-mer = territoires français hors Europe | N153: 🟡 Intermédiaire | O153: Connaître l'organisation territoriale de la France. | P153: Outre-mer; DROM; COM; Territoires | Q153: 📚 Thématique 4 – Géographie 📖 Glossaire - Outre-mer - DROM - COM | R153: Oui | S153: Oui | T153: Oui | U153: À vérifier | V153: QUESTIONS_THEMATIQUE_4.md | W153: QCM source
A154: CR-T4-026 | B154: CR | C154: 4 | D154: Histoire, géographie, patrimoine et culture | E154: Géographie de la France | F154: Quelle chaîne de montagnes est située entre la France et l'Espagne ? | G154: Les Pyrénées. | H154: Les Alpes. | I154: Le Massif central. | J154: Les Vosges. | K154: A | L154: Les Pyrénées forment une frontière naturelle entre la France et l'Espagne. | M154: Retenez : Pyrénées = montagnes entre France et Espagne | N154: 🟡 Intermédiaire | O154: Connaître les principaux reliefs de la France. | P154: Pyrénées; Montagnes; Espagne | Q154: 📚 Thématique 4 – Géographie 📖 Glossaire - Pyrénées | R154: Oui | S154: Oui | T154: Oui | U154: À vérifier | V154: QUESTIONS_THEMATIQUE_4.md | W154: Réponses à ne pas accepter + banque thématique
A155: CR-T4-027 | B155: CR | C155: 4 | D155: Histoire, géographie, patrimoine et culture | E155: Histoire de France | F155: Quelle île française se trouve dans l'océan Indien ? | G155: La Réunion. | H155: La Corse. | I155: La Guadeloupe. | J155: La Martinique. | K155: A | L155: La Réunion est un département et une région d'outre-mer situé dans l'océan Indien, à l'est de Madagascar. | M155: Retenez : La Réunion est entourée par l'océan Indien | N155: 🟡 Intermédiaire | O155: Connaître la géographie de la France d'outre-mer. | P155: La Réunion; Océan Indien; Outre-mer | Q155: 📚 Thématique 4 – Outre-mer 📖 Glossaire - La Réunion | R155: Oui | S155: Oui | T155: Oui | U155: À vérifier | V155: QUESTIONS_THEMATIQUE_4.md | W155: Réponses à ne pas accepter + banque thématique
A156: CR-T4-028 | B156: CR | C156: 4 | D156: Histoire, géographie, patrimoine et culture | E156: Histoire de France | F156: Quelle est la population approximative de la France en 2025 ? | G156: 50 millions. | H156: 68 millions. | I156: 60 millions. | J156: 57 millions. | K156: B | L156: En 2025, la France compte environ 68 millions d'habitants. Ce chiffre peut évoluer légèrement au fil des années. | M156: Retenez le mot-clé : Population France = 68 millions | N156: 🟡 Intermédiaire | O156: Connaître les grands repères démographiques. | P156: Population; France; 68 millions | Q156: 📚 Thématique 4 – Géographie 📖 Glossaire - Population française | R156: Oui | S156: Oui | T156: Oui | U156: À vérifier | V156: QUESTIONS_THEMATIQUE_4.md | W156: Réponses à ne pas accepter + banque thématique
A157: CR-T4-029 | B157: CR | C157: 4 | D157: Histoire, géographie, patrimoine et culture | E157: Géographie de la France | F157: Quel fleuve traverse Paris ? | G157: La Loire. | H157: Le Rhône. | I157: La Garonne. | J157: La Seine. | K157: D | L157: La Seine traverse Paris avant de se jeter dans la Manche, au Havre. | M157: Retenez comme moyen mnémotechnique que Paris regorge de théâtres et donc de scènes (Seine) | N157: 🟡 Intermédiaire | O157: Connaître les principaux fleuves français. | P157: Seine; Paris; Fleuve | Q157: 📚 Thématique 4 – Géographie 📖 Glossaire - Seine | R157: Oui | S157: Oui | T157: Oui | U157: À vérifier | V157: QUESTIONS_THEMATIQUE_4.md | W157: Réponses à ne pas accepter + banque thématique
A158: CR-T4-030 | B158: CR | C158: 4 | D158: Histoire, géographie, patrimoine et culture | E158: Géographie de la France | F158: Lequel de ces pays partage des frontières terrestres avec la France ? | G158: Le Royaume-Uni. | H158: L'Irlande. | I158: La Belgique. | J158: Le Danemark. | K158: C | L158: La Belgique partage une frontière terrestre avec la France. Le Royaume-Uni est séparé de la France par la Manche. | M158: Retenez : Belgique = voisin terrestre | N158: 🟡 Intermédiaire | O158: Connaître les pays voisins de la France. | P158: Belgique; Frontière; France | Q158: 📚 Thématique 4 – Géographie 📖 Glossaire - Pays frontaliers --- | R158: Oui | S158: Oui | T158: Oui | U158: À vérifier | V158: QUESTIONS_THEMATIQUE_4.md | W158: QCM source
A159: CR-T4-036 | B159: CR | C159: 4 | D159: Histoire, géographie, patrimoine et culture | E159: Histoire de France | F159: Quelle ville française fait partie des 10 plus grandes métropoles du pays ? | G159: Lyon. | H159: Vichy. | I159: Lourdes. | J159: Colmar. | K159: A | L159: La France compte plusieurs grandes métropoles qui concentrent une grande partie de la population, des emplois et des activités économiques. | M159: Retenez : Lyon est la 2e ville la plus peuplée (plus d'un million d'habitants) | N159: 🟡 Intermédiaire | O159: Connaître les principales villes françaises. | P159: Métropole; Ville; France | Q159: 📚 Thématique 4 – Géographie 📖 Glossaire - Métropole | R159: Oui | S159: Oui | T159: Oui | U159: À vérifier | V159: QUESTIONS_THEMATIQUE_4.md | W159: Réponses à ne pas accepter + banque thématique
A160: CR-T4-037 | B160: CR | C160: 4 | D160: Histoire, géographie, patrimoine et culture | E160: Patrimoine et culture | F160: Lequel de ces départements de France est le plus touristique ? | G160: Paris. | H160: Creuse. | I160: Lozère. | J160: Haute-Marne. | K160: A | L160: Paris est le département français qui accueille le plus grand nombre de visiteurs grâce à son patrimoine, ses musées et ses monuments. | M160: Retenez le mot-clé : Paris. | N160: 🔴 Difficile | O160: Connaître les grands repères touristiques de la France. | P160: Paris; Tourisme; Patrimoine | Q160: 📚 Thématique 4 – Tourisme 📖 Glossaire - Paris | R160: Oui | S160: Oui | T160: Oui | U160: À vérifier | V160: QUESTIONS_THEMATIQUE_4.md | W160: QCM source
A161: CR-T4-038 | B161: CR | C161: 4 | D161: Histoire, géographie, patrimoine et culture | E161: Patrimoine et culture | F161: Quand peut-on visiter gratuitement des lieux culturels en France ? | G161: Le 14 juillet. | H161: Le 25 décembre. | I161: Lors des Journées européennes du patrimoine. | J161: Tous les dimanches. | K161: C | L161: Chaque année, les Journées européennes du patrimoine permettent au public de visiter gratuitement de nombreux monuments et lieux habituellement fermés ou payants. | M161: Retenez: Journée du patrimoine = visite gratuite (musées, monuments…) | N161: 🟡 Intermédiaire | O161: Connaître les grands événements culturels. | P161: Patrimoine; Culture; Journées du patrimoine | Q161: 📚 Thématique 4 – Culture 📖 Glossaire - Journées européennes du patrimoine | R161: Oui | S161: Oui | T161: Oui | U161: À vérifier | V161: QUESTIONS_THEMATIQUE_4.md | W161: Réponses à ne pas accepter + banque thématique
A162: CR-T4-039 | B162: CR | C162: 4 | D162: Histoire, géographie, patrimoine et culture | E162: Patrimoine et culture | F162: Combien de personnes parlent français dans le monde ? | G162: 50 millions. | H162: 120 millions. | I162: 320 millions. | J162: 700 millions. | K162: C | L162: Le français est parlé sur les cinq continents par environ 320 millions de personnes. Ce chiffre évolue régulièrement. | M162: Retenez : 320 millions de personnes parlent français | N162: 🟡 Intermédiaire | O162: Connaître le rayonnement international de la langue française. | P162: Francophonie; Français; 320 millions | Q162: 📚 Thématique 4 – Culture 📖 Glossaire - Francophonie | R162: Oui | S162: Oui | T162: Oui | U162: À vérifier | V162: QUESTIONS_THEMATIQUE_4.md | W162: Réponses à ne pas accepter + banque thématique
... A205: CR-T5-032 | B205: CR | C205: 5 | D205: Vivre dans la société française | E205: Éducation et famille | F205: À l'école, un enfant en situation de handicap : | G205: Doit obligatoirement être scolarisé dans un établissement spécialisé. | H205: A le droit d'être scolarisé avec les autres élèves lorsque cela est possible, avec les accompagnements nécessaires. | I205: Ne peut pas fréquenter l'école publique. | J205: Est dispensé d'instruction. | K205: B | L205: L'école française favorise l'école inclusive. Les élèves en situation de handicap ont le droit d'être scolarisés avec les autres élèves lorsque cela est possible, avec les aménagements et accompagnements nécessaires. | M205: Retenez : Les éléves handicapés ont le droit d'être avec les autres élèves = école inclusive | N205: 🟡 Intermédiaire | O205: Connaître les principes de l'école inclusive. | P205: Handicap; École inclusive; Scolarisation | Q205: 📚 Thématique 5 – Éducation 📖 Glossaire - École inclusive - Handicap | R205: Oui | S205: Oui | T205: Oui | U205: À vérifier | V205: QUESTIONS_THEMATIQUE_5.md | W205: QCM source

Sheet Contrôle_Qualité
A1: Contrôle qualité — Banque Carte de résident
A3: Indicateur | B3: Formule / résultat | C3: Objectif | E3: Bonne réponse | F3: Nombre
A4: Nombre total de questions | B4: =COUNTA(Banque_CR!A2:A1000) -> 204 | C4: 204 | E4: A | F4: =COUNTIF(Banque_CR!K2:K1000,"A") -> 50
A5: Thématique 1 | B5: =COUNTIF(Banque_CR!C2:C1000,1) -> 39 | C5: 39 | E5: B | F5: =COUNTIF(Banque_CR!K2:K1000,"B") -> 51
A6: Thématique 2 | B6: =COUNTIF(Banque_CR!C2:C1000,2) -> 50 | C6: 50 | E6: C | F6: =COUNTIF(Banque_CR!K2:K1000,"C") -> 51
A7: Thématique 3 | B7: =COUNTIF(Banque_CR!C2:C1000,3) -> 38 | C7: 38 | E7: D | F7: =COUNTIF(Banque_CR!K2:K1000,"D") -> 52
A8: Thématique 4 | B8: =COUNTIF(Banque_CR!C2:C1000,4) -> 45 | C8: 45 | E8: Total | F8: =SUM(F4:F7) -> 204
A9: Thématique 5 | B9: =COUNTIF(Banque_CR!C2:C1000,5) -> 32 | C9: 32
A10: Questions à vérifier | B10: =COUNTIF(Banque_CR!U2:U1000,"À vérifier") -> 204 | C10: Relecture éditoriale
A13: Lecture éditoriale recommandée
A14: 1 | B14: Vérifier la précision factuelle de chaque QCM.
A15: 2 | B15: Valider la crédibilité des distracteurs générés à partir des réponses erronées du fichier source.
A16: 3 | B16: Améliorer les astuces mémoire génériques lors de la relecture thématique.
A17: 4 | B17: Passer le statut de « À vérifier » à « Validée » après contrôle.
A18: 5 | B18: Générer ensuite les fichiers Markdown ChatMD depuis cette banque source.

Sheet Standard_V2
A1: Standard Banque officielle NovaFrate V2
A3: Champ | B3: Obligatoire | C3: Règle | D3: Module utilisateur
A4: ID | B4: Oui | C4: Identifiant unique CR-Tx-xxx | D4: Tous
A5: Question | B5: Oui | C5: Une seule idée, formulation simple | D5: Tous
A6: Réponses A-D | B6: Oui | C6: 4 propositions plausibles et homogènes | D6: Tous
A7: Bonne réponse | B7: Oui | C7: Une seule lettre A/B/C/D | D7: Score
A8: Explication pédagogique | B8: Oui | C8: Courte et claire | D8: Diagnostic + révision
A9: Astuce mémoire | B9: Oui | C9: Une phrase maximum | D9: Révision
A10: Difficulté | B10: Oui | C10: 🟢 / 🟡 / 🔴 | D10: Diagnostic + statistiques
A11: Compétence | B11: Oui | C11: Une compétence observable | D11: Remédiation
A12: Mots-clés | B12: Oui | C12: 3 à 6 termes | D12: Recherche
A13: Ressources | B13: Oui | C13: Cours et glossaire correspondants | D13: Révision
A14: Statut | B14: Oui | C14: À vérifier → Validée → Publiée | D14: Production

Sheet Sources_Fichiers
A1: Fichiers sources intégrés
A3: Thématique | B3: Fichier | C3: Nombre de questions | D3: Usage
A4: 1 | B4: QUESTIONS_THEMATIQUE_1(1).md | C4: 39 | D4: Source éditoriale de la banque CR
A5: 2 | B5: QUESTIONS_THEMATIQUE_2.md | C5: 50 | D5: Source éditoriale de la banque CR
A6: 3 | B6: QUESTIONS_THEMATIQUE_3.md | C6: 38 | D6: Source éditoriale de la banque CR
A7: 4 | B7: QUESTIONS_THEMATIQUE_4.md | C7: 45 | D7: Source éditoriale de la banque CR
A8: 5 | B8: QUESTIONS_THEMATIQUE_5.md | C8: 32 | D8: Source éditoriale de la banque CR

Sheet Banque_CR_Chatbot
A1: ID_QUESTION | B1: TYPE_EXAMEN | C1: ORDRE_THEME | D1: ID_THEME | E1: TITRE_THEME | F1: ID_CHAPITRE | G1: TITRE_CHAPITRE | H1: QUESTION | I1: REPONSE_A | J1: REPONSE_B | K1: REPONSE_C | L1: REPONSE_D | M1: BONNE_REPONSE | N1: EXPLICATION_PEDAGOGIQUE | O1: ASTUCE_MEMOIRE | P1: DIFFICULTE | Q1: COMPETENCE | R1: MOTS_CLES | S1: RESSOURCES_A_REVOIR | T1: DIAGNOSTIC | U1: REVISION | V1: EXAMEN_BLANC | W1: ACTIF | X1: FICHIER_SOURCE | Y1: ORIGINE_DISTRACTEURS
A2: CR-T1-001 | B2: Carte de résident | C2: 3 | D2: T3 | E2: Droits et devoirs | F2: T3_CH02 | G2: Les obligations et les devoirs | H2: Parmi les propositions suivantes, laquelle constitue une participation citoyenne ? | I2: Obtenir une carte d'identité française. | J2: S'inscrire à la Sécurité sociale. | K2: Voter aux élections. | L2: Travailler dans une entreprise. | M2: C | N2: La participation citoyenne consiste à prendre part à la vie démocratique du pays. Le vote est l'une des principales formes de participation citoyenne. | O2: Retenez le mot-clé : Citoyenneté = droit de voter aux élections | P2: 🟢 Facile | Q2: Connaître les formes de participation à la vie démocratique. | R2: Citoyenneté; Vote; Élections | S2: 📚 Thématique 1 – Principes et valeurs de la République 📖 Glossaire - Citoyenneté - Vote | T2: Oui | U2: Oui | V2: Oui | W2: Oui | X2: QUESTIONS_THEMATIQUE_1(1).md | Y2: QCM source
A3: CR-T1-002 | B3: Carte de résident | C3: 1 | D3: T1 | E3: Principes et valeurs de la République | F3: T1_CH01 | G3: Connaître et comprendre la République | H3: Que garantit la liberté d'expression ? | I3: Le droit d'insulter les autres. | J3: Le droit de diffamer. | K3: Le droit d'exprimer librement ses opinions dans le respect de la loi. | L3: Le droit d'inciter à la haine. | M3: C | N3: La liberté d'expression est une liberté fondamentale. Elle permet à chacun d'exprimer ses idées, tout en respectant les lois et les autres personnes. | O3: Retenez le mot-clé : Liberté d'expression = exprimer ses opinions | P3: 🟢 Facile | Q3: Comprendre les libertés fondamentales. | R3: Liberté d'expression; Opinion; Libertés | S3: 📚 Thématique 1 – Libertés fondamentales 📖 Glossaire - Liberté d'expression | T3: Oui | U3: Oui | V3: Oui | W3: Oui | X3: QUESTIONS_THEMATIQUE_1(1).md | Y3: Réponses à ne pas accepter + banque thématique
A4: CR-T1-003 | B4: Carte de résident | C4: 5 | D4: T5 | E4: Vivre dans la société française | F4: T5_CH01 | G4: Les démarches administratives | H4: À quoi sert un titre de séjour ? | I4: À obtenir automatiquement la nationalité française. | J4: À voter aux élections. | K4: À remplacer une carte d'identité. | L4: À autoriser un étranger à séjourner légalement en France. | M4: D | N4: Le titre de séjour est un document officiel qui autorise une personne étrangère à résider en France pendant une durée déterminée ou permanente, selon sa situation. | O4: Retenez le mot-clé : Titre de séjour = document pour habiter en France | P4: 🟡 Intermédiaire | Q4: Connaître les principaux documents administratifs liés au séjour. | R4: Titre de séjour; Séjour; France | S4: 📚 Thématique 1 – Vie administrative 📖 Glossaire - Titre de séjour | T4: Oui | U4: Oui | V4: Oui | W4: Oui | X4: QUESTIONS_THEMATIQUE_1(1).md | Y4: Réponses à ne pas accepter + banque thématique
A5: CR-T1-004 | B5: Carte de résident | C5: 1 | D5: T1 | E5: Principes et valeurs de la République | F5: T1_CH01 | G5: Connaître et comprendre la République | H5: La liberté de circulation permet à toute personne de : | I5: S'installer sur n'importe quel terrain privé. | J5: Se déplacer librement sur le territoire national et à l'étranger. | K5: Conduire n'importe quel véhicule sans permis. | L5: Voyager librement sans papiers d'identité dans toute l'Europe. | M5: B | N5: La liberté de circulation permet à chacun de se déplacer librement, dans le respect des lois et des règles applicables. | O5: Retenez le mot-clé : Liberté de circulation = se déplacer | P5: 🟡 Intermédiaire | Q5: Comprendre les libertés fondamentales. | R5: Liberté de circulation; Déplacement; France | S5: 📚 Thématique 1 – Libertés fondamentales 📖 Glossaire - Liberté de circulation | T5: Oui | U5: Oui | V5: Oui | W5: Oui | X5: QUESTIONS_THEMATIQUE_1(1).md | Y5: QCM source
A6: CR-T1-005 | B6: Carte de résident | C6: 1 | D6: T1 | E6: Principes et valeurs de la République | F6: T1_CH03 | G6: Les symboles de la République française | H6: Sur quel site internet peut-on retrouver les symboles de la République française ? | I6: Sur le site de l'Élysée. | J6: Le site de la CAF. | K6: France Travail. | L6: Ameli. | M6: A | N6: Le site officiel de la Présidence de la République présente les symboles de la République française, notamment le drapeau, Marianne, la Marseillaise et la devise. | O6: Retenez : Site internet officiel montre les symboles | P6: 🟡 Intermédiaire | Q6: Identifier les ressources officielles de la République française. | R6: Élysée; République; Symboles | S6: 📚 Thématique 1 – Symboles de la République 📖 Glossaire - Symboles de la République | T6: Oui | U6: Oui | V6: Oui | W6: Oui | X6: QUESTIONS_THEMATIQUE_1(1).md | Y6: Réponses à ne pas accepter + banque thématique
A7: CR-T1-006 | B7: Carte de résident | C7: 1 | D7: T1 | E7: Principes et valeurs de la République | F7: T1_CH03 | G7: Les symboles de la République française | H7: Complétez ces paroles de la Marseillaise : « Aux armes [...] ! Formez vos bataillons. » | I7: Français. | J7: Soldats. | K7: Amis. | L7: Citoyens. | M7: D | N7: La Marseillaise est l'hymne national français. Chaque citoyen est invité à connaître ses paroles et leur signification. | O7: Retenez : Les citoyens = habitants de la France | P7: 🟡 Intermédiaire | Q7: Connaître les symboles de la République. | R7: Marseillaise; Citoyens; Hymne national | S7: 📚 Thématique 1 – Symboles de la République 📖 Glossaire - Marseillaise | T7: Oui | U7: Oui | V7: Oui | W7: Oui | X7: QUESTIONS_THEMATIQUE_1(1).md | Y7: Réponses à ne pas accepter + banque thématique
A8: CR-T1-007 | B8: Carte de résident | C8: 1 | D8: T1 | E8: Principes et valeurs de la République | F8: T1_CH03 | G8: Les symboles de la République française | H8: Complétez les paroles de la Marseillaise : « Allons enfants de la Patrie [...] » | I8: Le jour de gloire est arrivé. | J8: Le droit d'exprimer librement ses opinions dans le respect de la loi. | K8: À autoriser un étranger à séjourner légalement en France. | L8: Se déplacer librement sur le territoire national et à l'étranger. | M8: A | N8: Ces paroles ouvrent la Marseillaise, l'hymne national de la République française. | O8: Retenez : Gloire = grandeur | P8: 🟡 Intermédiaire | Q8: Connaître les symboles de la République. | R8: Marseillaise; Hymne | S8: 📚 Thématique 1 – Symboles de la République 📖 Glossaire - Marseillaise | T8: Oui | U8: Oui | V8: Oui | W8: Oui | X8: QUESTIONS_THEMATIQUE_1(1).md | Y8: Banque thématique + génération éditoriale
A9: CR-T1-008 | B9: Carte de résident | C9: 1 | D9: T1 | E9: Principes et valeurs de la République | F9: T1_CH04 | G9: La laïcité | H9: En application de la liberté individuelle, quelle proposition est correcte ? Une personne peut : | I9: Refuser de respecter les lois si elles sont contraires à ses principes. | J9: Imposer ses idées aux autres. | K9: Choisir ses propres règles. | L9: Choisir sa religion ou ne pas en avoir. | M9: D | N9: En France, chacun est libre de pratiquer une religion, d'en changer ou de ne pas avoir de religion. Cette liberté est protégée par la loi. | O9: Retenez : chacun peut choisir sa religion | P9: 🟡 Intermédiaire | Q9: Comprendre les libertés individuelles. | R9: Religion; Liberté; Laïcité | S9: 📚 Thématique 1 – Libertés fondamentales 📖 Glossaire - Liberté de conscience | T9: Oui | U9: Oui | V9: Oui | W9: Oui | X9: QUESTIONS_THEMATIQUE_1(1).md | Y9: QCM source
A10: CR-T1-009 | B10: Carte de résident | C10: 1 | D10: T1 | E10: Principes et valeurs de la République | F10: T1_CH04 | G10: La laïcité | H10: Concernant la pratique de la religion, quelle proposition est correcte ? | I10: Chacun est libre de pratiquer sa religion. | J10: Les signes religieux sont interdits dans la rue. | K10: La religion ne peut être pratiquée qu'à la maison. | L10: Les lieux de culte sont financés par tous les services publics. | M10: A | N10: La liberté religieuse est garantie en France. Chacun est libre de croire, de pratiquer sa religion ou de ne pas avoir de religion, dans le respect de la loi. | O10: Retenez : chacun peut choisir sa religion | P10: 🟡 Intermédiaire | Q10: Comprendre la liberté religieuse. | R10: Religion; Liberté; Laïcité | S10: 📚 Thématique 1 – Laïcité 📖 Glossaire - Liberté de religion | T10: Oui | U10: Oui | V10: Oui | W10: Oui | X10: QUESTIONS_THEMATIQUE_1(1).md | Y10: QCM source
A11: CR-T1-010 | B11: Carte de résident | C11: 5 | D11: T5 | E11: Vivre dans la société française | F11: T5_CH04 | G11: La parentalité | H11: En tant que parent, peut-on refuser que son enfant participe aux cours de sport à l'école parce qu'ils sont mixtes ? | I11: Oui. | J11: Oui si les parents le souhaitent. | K11: Oui, dans tous les cas. | L11: Non. | M11: D | N11: Les cours de sport font partie des enseignements obligatoires. La mixité entre les filles et les garçons est un principe de l'école de la République. | O11: Retenez : Cours = obligatoire | P11: 🟡 Intermédiaire | Q11: Connaître les principes de l'école de la République. | R11: École; Mixité; Sport; Égalité | S11: 📚 Thématique 1 – École et République 📖 Glossaire - Mixité - École publique | T11: Oui | U11: Oui | V11: Oui | W11: Oui | X11: QUESTIONS_THEMATIQUE_1(1).md | Y11: Réponses à ne pas accepter + banque thématique
A12: CR-T1-011 | B12: Carte de résident | C12: 1 | D12: T1 | E12: Principes et valeurs de la République | F12: T1_CH02 | G12: La devise de la République française | H12: Quelle est la devise de la France ? | I12: Liberté, Justice, Egalité, | J12: Travail, Famille, Patrie. | K12: Liberté, Égalité, Fraternité. | L12: Égalité, Solidarité, Liberté, | M12: C | N12: La devise de la République française est « Liberté, Égalité, Fraternité ». Elle exprime les valeurs fondamentales de la République. | O12: Retenez : La devise = valeurs représentant la France | P12: 🟡 Intermédiaire | Q12: Connaître les symboles de la République. | R12: Devise; République; Liberté; Égalité; Fraternité | S12: 📚 Thématique 1 – Valeurs de la République 📖 Glossaire - Devise républicaine | T12: Oui | U12: Oui | V12: Oui | W12: Oui | X12: QUESTIONS_THEMATIQUE_1(1).md | Y12: Réponses à ne pas accepter + banque thématique
A13: CR-T1-012 | B13: Carte de résident | C13: 1 | D13: T1 | E13: Principes et valeurs de la République | F13: T1_CH01 | G13: Connaître et comprendre la République | H13: La répudiation de sa femme est : | I13: Autorisée avec l'accord d'un juge. | J13: Interdite par la loi française. | K13: Légale si elle est prévue dans le contrat de mariage. | L13: Autorisée avec l'accord de la famille. | M13: B | N13: En France, les femmes et les hommes disposent des mêmes droits. La répudiation n'est pas reconnue par le droit français. | O13: Retenez le mot-clé : Égalité. | P13: 🟢 Facile | Q13: Connaître le principe d'égalité entre les femmes et les hommes. | R13: Égalité; Mariage; Répudiation | S13: 📚 Thématique 1 – Égalité 📖 Glossaire - Égalité femmes-hommes | T13: Oui | U13: Oui | V13: Oui | W13: Oui | X13: QUESTIONS_THEMATIQUE_1(1).md | Y13: QCM source
... A205: CR-T5-032 | B205: Carte de résident | C205: 5 | D205: T5 | E205: Vivre dans la société française | F205: T5_CH04 | G205: La parentalité | H205: À l'école, un enfant en situation de handicap : | I205: Doit obligatoirement être scolarisé dans un établissement spécialisé. | J205: A le droit d'être scolarisé avec les autres élèves lorsque cela est possible, avec les accompagnements nécessaires. | K205: Ne peut pas fréquenter l'école publique. | L205: Est dispensé d'instruction. | M205: B | N205: L'école française favorise l'école inclusive. Les élèves en situation de handicap ont le droit d'être scolarisés avec les autres élèves lorsque cela est possible, avec les aménagements et accompagnements nécessaires. | O205: Retenez : Les éléves handicapés ont le droit d'être avec les autres élèves = école inclusive | P205: 🟡 Intermédiaire | Q205: Connaître les principes de l'école inclusive. | R205: Handicap; École inclusive; Scolarisation | S205: 📚 Thématique 5 – Éducation 📖 Glossaire - École inclusive - Handicap | T205: Oui | U205: Oui | V205: Oui | W205: Oui | X205: QUESTIONS_THEMATIQUE_5.md | Y205: QCM source

Sheet Contrôle_Mini_QCM
A1: CONTRÔLE DE COUVERTURE — MINI-QCM CARTE DE RÉSIDENT
A2: Chaque chapitre doit disposer d’au moins 5 questions actives pour permettre à Python de tirer un mini-QCM sans doublon.
A4: ID_THEME | B4: TITRE_THEME | C4: ID_CHAPITRE | D4: TITRE_CHAPITRE | E4: NB_QUESTIONS_ACTIVES | F4: ECART_A_5 | G4: STATUT
A5: T1 | B5: Principes et valeurs de la République | C5: T1_CH01 | D5: Connaître et comprendre la République | E5: =COUNTIFS(Banque_CR_Chatbot!$F$2:$F$205,C5,Banque_CR_Chatbot!$W$2:$W$205,"Oui") -> 8 | F5: =MAX(0,5-E5) -> 0 | G5: =IF(E5>=5,"OK","INCOMPLET") -> OK
A6: T1 | B6: Principes et valeurs de la République | C6: T1_CH02 | D6: La devise de la République française | E6: =COUNTIFS(Banque_CR_Chatbot!$F$2:$F$205,C6,Banque_CR_Chatbot!$W$2:$W$205,"Oui") -> 2 | F6: =MAX(0,5-E6) -> 3 | G6: =IF(E6>=5,"OK","INCOMPLET") -> INCOMPLET
A7: T1 | B7: Principes et valeurs de la République | C7: T1_CH03 | D7: Les symboles de la République française | E7: =COUNTIFS(Banque_CR_Chatbot!$F$2:$F$205,C7,Banque_CR_Chatbot!$W$2:$W$205,"Oui") -> 8 | F7: =MAX(0,5-E7) -> 0 | G7: =IF(E7>=5,"OK","INCOMPLET") -> OK
A8: T1 | B8: Principes et valeurs de la République | C8: T1_CH04 | D8: La laïcité | E8: =COUNTIFS(Banque_CR_Chatbot!$F$2:$F$205,C8,Banque_CR_Chatbot!$W$2:$W$205,"Oui") -> 15 | F8: =MAX(0,5-E8) -> 0 | G8: =IF(E8>=5,"OK","INCOMPLET") -> OK
A9: T1 | B9: Principes et valeurs de la République | C9: T1_CH05 | D9: La langue de la République | E9: =COUNTIFS(Banque_CR_Chatbot!$F$2:$F$205,C9,Banque_CR_Chatbot!$W$2:$W$205,"Oui") -> 1 | F9: =MAX(0,5-E9) -> 4 | G9: =IF(E9>=5,"OK","INCOMPLET") -> INCOMPLET
A10: T1 | B10: Principes et valeurs de la République | C10: T1_CH06 | D10: Le contrat d’engagement à respecter les principes de la République | E10: =COUNTIFS(Banque_CR_Chatbot!$F$2:$F$205,C10,Banque_CR_Chatbot!$W$2:$W$205,"Oui") -> 0 | F10: =MAX(0,5-E10) -> 5 | G10: =IF(E10>=5,"OK","INCOMPLET") -> INCOMPLET
A11: T2 | B11: Système institutionnel et politique | C11: T2_CH01 | D11: État de droit et séparation des pouvoirs | E11: =COUNTIFS(Banque_CR_Chatbot!$F$2:$F$205,C11,Banque_CR_Chatbot!$W$2:$W$205,"Oui") -> 22 | F11: =MAX(0,5-E11) -> 0 | G11: =IF(E11>=5,"OK","INCOMPLET") -> OK
A12: T2 | B12: Système institutionnel et politique | C12: T2_CH02 | D12: Démocratie et droit de vote | E12: =COUNTIFS(Banque_CR_Chatbot!$F$2:$F$205,C12,Banque_CR_Chatbot!$W$2:$W$205,"Oui") -> 5 | F12: =MAX(0,5-E12) -> 0 | G12: =IF(E12>=5,"OK","INCOMPLET") -> OK
A13: T2 | B13: Système institutionnel et politique | C13: T2_CH03 | D13: Organisation de la République française | E13: =COUNTIFS(Banque_CR_Chatbot!$F$2:$F$205,C13,Banque_CR_Chatbot!$W$2:$W$205,"Oui") -> 8 | F13: =MAX(0,5-E13) -> 0 | G13: =IF(E13>=5,"OK","INCOMPLET") -> OK
A14: T2 | B14: Système institutionnel et politique | C14: T2_CH04 | D14: Les institutions européennes | E14: =COUNTIFS(Banque_CR_Chatbot!$F$2:$F$205,C14,Banque_CR_Chatbot!$W$2:$W$205,"Oui") -> 15 | F14: =MAX(0,5-E14) -> 0 | G14: =IF(E14>=5,"OK","INCOMPLET") -> OK
A15: T3 | B15: Droits et devoirs | C15: T3_CH01 | D15: Les droits fondamentaux | E15: =COUNTIFS(Banque_CR_Chatbot!$F$2:$F$205,C15,Banque_CR_Chatbot!$W$2:$W$205,"Oui") -> 22 | F15: =MAX(0,5-E15) -> 0 | G15: =IF(E15>=5,"OK","INCOMPLET") -> OK
A16: T3 | B16: Droits et devoirs | C16: T3_CH02 | D16: Les obligations et les devoirs | E16: =COUNTIFS(Banque_CR_Chatbot!$F$2:$F$205,C16,Banque_CR_Chatbot!$W$2:$W$205,"Oui") -> 18 | F16: =MAX(0,5-E16) -> 0 | G16: =IF(E16>=5,"OK","INCOMPLET") -> OK
... A23: T5 | B23: Vivre dans la société française | C23: T5_CH04 | D23: La parentalité | E23: =COUNTIFS(Banque_CR_Chatbot!$F$2:$F$205,C23,Banque_CR_Chatbot!$W$2:$W$205,"Oui") -> 14 | F23: =MAX(0,5-E23) -> 0 | G23: =IF(E23>=5,"OK","INCOMPLET") -> OK

Sheet Référentiel_Chapitres
A1: ID_THEME | B1: TITRE_THEME | C1: ID_CHAPITRE | D1: TITRE_CHAPITRE | E1: SOURCE_REFERENCE
A2: T1 | B2: Principes et valeurs de la République | C2: T1_CH01 | D2: Connaître et comprendre la République | E2: 03_REVISIONS
A3: T1 | B3: Principes et valeurs de la République | C3: T1_CH02 | D3: La devise de la République française | E3: 03_REVISIONS
A4: T1 | B4: Principes et valeurs de la République | C4: T1_CH03 | D4: Les symboles de la République française | E4: 03_REVISIONS
A5: T1 | B5: Principes et valeurs de la République | C5: T1_CH04 | D5: La laïcité | E5: 03_REVISIONS
A6: T1 | B6: Principes et valeurs de la République | C6: T1_CH05 | D6: La langue de la République | E6: 03_REVISIONS
A7: T1 | B7: Principes et valeurs de la République | C7: T1_CH06 | D7: Le contrat d’engagement à respecter les principes de la République | E7: 03_REVISIONS
A8: T2 | B8: Système institutionnel et politique | C8: T2_CH01 | D8: État de droit et séparation des pouvoirs | E8: 03_REVISIONS
A9: T2 | B9: Système institutionnel et politique | C9: T2_CH02 | D9: Démocratie et droit de vote | E9: 03_REVISIONS
A10: T2 | B10: Système institutionnel et politique | C10: T2_CH03 | D10: Organisation de la République française | E10: 03_REVISIONS
A11: T2 | B11: Système institutionnel et politique | C11: T2_CH04 | D11: Les institutions européennes | E11: 03_REVISIONS
A12: T3 | B12: Droits et devoirs | C12: T3_CH01 | D12: Les droits fondamentaux | E12: 03_REVISIONS
... A20: T5 | B20: Vivre dans la société française | C20: T5_CH04 | D20: La parentalité | E20: 03_REVISIONS
